tradelibs/__init__.py
tradelibs/ta.py
tradelibs-0.1.2.dist-info/LICENSE
tradelibs-0.1.2.dist-info/METADATA
tradelibs-0.1.2.dist-info/WHEEL
tradelibs-0.1.2.dist-info/top_level.txt
tradelibs-0.1.2.dist-info/RECORD
