Metadata-Version: 2.2
Name: tradelibs
Version: 0.1.2
Summary: Một thư viện hỗ trợ tính toán nhanh cho giao dịch tiền điện tử
Author-email: dinhluyen93 <dinhluyenbk93@gmail.com>
License: MIT
Project-URL: Documentation, https://github.com/dinhluyen93/tradelibs/docs
Project-URL: Source, https://github.com/dinhluyen93/tradelibs
Project-URL: Homepage, https://github.com/dinhluyen93/tradelibs
Project-URL: Tracker, https://github.com/dinhluyen93/tradelibs/issues
Project-URL: Release Notes, https://example.com/tradelibs/releases
Classifier: Development Status :: 3 - Alpha
Classifier: Intended Audience :: Developers
Classifier: License :: OSI Approved :: MIT License
Classifier: Programming Language :: Python :: 3.10
Classifier: Programming Language :: Python :: 3.11
Classifier: Programming Language :: Python :: 3.12
Classifier: Topic :: Software Development :: Libraries
Requires-Python: >=3.10
License-File: LICENSE
Requires-Dist: numpy>=2.2.2
